<?xml version="1.0" encoding="utf-8"?>
<ModMetaData>
	<name>Ranger (VPE)</name>
	<author>crazedmonkey231</author>
	<packageId>crazedmonkey231.ranger.vpe</packageId>
	<supportedVersions>
		<li>1.4</li>
	</supportedVersions>
	<description>*Fill This Out*</description>
    <loadAfter>
        <li>vanillaexpanded.vpsycastse</li>
    </loadAfter>
    <modDependencies>
        <li>
            <packageId>vanillaexpanded.vpsycastse</packageId>
            <displayName>Vanilla Psycasts Expanded</displayName>
            <steamWorkshopUrl>steam://url/CommunityFilePage/2842502659</steamWorkshopUrl>
        </li>
    </modDependencies>
</ModMetaData>